tpi/componentes/PC/PC.v
// Contador de Programa.

module PC (
    input wire clk,
    input [31:0] pcNext,
    output [31:0] pc
);

 [31:0] aux_pc;

// inicia en 0
initial begin
    aux_pc = 0;
end
    
always @(posedge clk ) begin
    aux_pc <= pcNext;
end

assign pc = aux_pc;

endmodule

tpi/componentes/PC/PC_tb.v
// Testbench_template

`default_nettype none
`define DUMPSTR(x) `"x.vcd`"
`timescale 100 ns / 10 ns

module PC_tb();

parameter DURATION = 10;

reg clk = 0;
always #0.5 clk = ~clk;

reg[31:0] pcNext;
wire[31:0] pc;

PC UUT (
          .clk(clk),
          .pcNext(pcNext),
          .pc(pc)
         );

integer i;

initial begin

  $dumpfile(`DUMPSTR(`VCD_OUTPUT));
  $dumpvars(0, PC_tb);

  for (i=0; i<10; i=i+1)
  begin
    $display ("Current loop # %0d", i);
    $display ("Current loop # %0b", i);
    #1
    pcNext = i;

  end

   #(DURATION) $display("End of simulation");
  $finish;
end

endmodule

tpi/Componentes/PC/PC_tb.vcd
$date
	Fri Nov 15 17:23:07 2024
$end
$version
	Icarus Verilog
$end
$timescale
	1ps
$end
$scope module PC_tb $end
$var wire 32 ! pc [31:0] $end
$var parameter 32 " DURATION $end
$var reg 1 # clk $end
$var reg 32 $ pcNext [31:0] $end
$var integer 32 % i [31:0] $end
$scope module UUT $end
$var wire 1 # clk $end
$var wire 32 & pc [31:0] $end
$var wire 32 ' pcNext [31:0] $end
$var reg 32 ( aux_pc [31:0] $end
$upscope $end
$upscope $end
$enddefinitions $end
$comment Show the parameter values. $end
$dumpall
b1010 "
$end
#0
$dumpvars
b0 (
bx '
b0 &
b0 %
bx $
0#
b0 !
$end
#50000
bx !
bx &
bx (
1#
#100000
0#
b1 %
b0 $
b0 '
#150000
b0 !
b0 &
b0 (
1#
#200000
0#
b10 %
b1 $
b1 '
#250000
b1 !
b1 &
b1 (
1#
#300000
0#
b11 %
b10 $
b10 '
#350000
b10 !
b10 &
b10 (
1#
#400000
0#
b100 %
b11 $
b11 '
#450000
b11 !
b11 &
b11 (
1#
#500000
0#
b101 %
b100 $
b100 '
#550000
b100 !
b100 &
b100 (
1#
#600000
0#
b110 %
b101 $
b101 '
#650000
b101 !
b101 &
b101 (
1#
#700000
0#
b111 %
b110 $
b110 '
#750000
b110 !
b110 &
b110 (
1#
#800000
0#
b1000 %
b111 $
b111 '
#850000
b111 !
b111 &
b111 (
1#
#900000
0#
b1001 %
b1000 $
b1000 '
#950000
b1000 !
b1000 &
b1000 (
1#
#1000000
0#
b1010 %
b1001 $
b1001 '
#1050000
b1001 !
b1001 &
b1001 (
1#
