tpi/rv32i/parts/UC/componentes/aluDeco/aluDeco.v
// Decodificador de la ALU
/*
    ALUop   funct3  inst    ALUcontrol
    00      x       lw,sw   000(add)
    01      x       beq     001(sub)
    10      000     add     000(add)
            000     sub     001(sub)
            010     slt     101(slt)
            110     or      011(or)
            111     and     010(and)

*/
module aluDeco (
    input wire op, //op[5]
    input wire f7,
    input [2:0] f3,
    input [1:0] aluOp,
    output [2:0] ALUControl
);

reg [2:0] aux_ALUControl;

always @(*) begin
    case (aluOp)
        0:
            begin
                aux_ALUControl = 3'b000; //add
            end 
        1:
            begin
                aux_ALUControl = 3'b001; //sub
            end
        2: 
            //
            begin
                case (f3)
                    0:
                        begin
                            //subs if 11, else add
                            aux_ALUControl = (f7 & op) ? 3'b001 : 3'b000; 
                        end
                    2:
                        begin
                            aux_ALUControl = 3'b101; //slt
                        end
                    6:
                        begin
                            aux_ALUControl = 3'b011; //or
                        end
                    7:
                        begin   
                            aux_ALUControl = 3'b010; //and
                        end
                    default: 
                        begin
                            aux_ALUControl = 3'bxxx; //fail..
                        end
                endcase
            end
        default: 
            begin
                aux_ALUControl = 3'bxxx; //fail..
            end
    endcase
end

assign ALUControl = aux_ALUControl;

endmodule

tpi/rv32i/parts/UC/componentes/aluDeco/aluDeco_tb.v
// Testbench_template
// Worked
`default_nettype none
`define DUMPSTR(x) `"x.vcd`"
`timescale 100 ns / 10 ns

module aluDeco_tb();

parameter DURATION = 10;

reg clk = 0;
always #0.5 clk = ~clk;

reg op;
reg f7;
reg[2:0] f3;
reg[1:0] aluOp;
wire[2:0] ALUControl;

aluDeco UUT (
          .op(op),
          .f7(f7),
          .f3(f3),
          .aluOp(aluOp),
          .ALUControl(ALUControl)
         );

integer i;

initial begin

  $dumpfile(`DUMPSTR(`VCD_OUTPUT));
  $dumpvars(0, aluDeco_tb);

    f7 = 1;
    op = 1;

    #1
    aluOp = 0;
    #1
    aluOp = 1;
    #1
    aluOp = 2;
    f3 = 0;
    
    #1
    aluOp = 2;
    f3 = 0;
    f7 = 0;

    #1
    aluOp = 2;
    f3 = 2;
    #1
    aluOp = 2;
    f3 = 6;
    #1
    aluOp = 2;
    f3 = 7;
    #1
    aluOp = 2;
    f3 = 1;
    #1
    aluOp = 3;
    #(DURATION) $display("End of simulation");
  $finish;
end

endmodule

tpi/rv32i/parts/UC/componentes/aluDeco/aluDeco_tb.vcd
$date
	Sat Nov 16 10:49:40 2024
$end
$version
	Icarus Verilog
$end
$timescale
	1ps
$end
$scope module aluDeco_tb $end
$var wire 3 ! ALUControl [2:0] $end
$var parameter 32 " DURATION $end
$var reg 2 # aluOp [1:0] $end
$var reg 1 $ clk $end
$var reg 3 % f3 [2:0] $end
$var reg 1 & f7 $end
$var reg 1 ' op $end
$scope module UUT $end
$var wire 3 ( ALUControl [2:0] $end
$var wire 2 ) aluOp [1:0] $end
$var wire 3 * f3 [2:0] $end
$var wire 1 & f7 $end
$var wire 1 ' op $end
$var reg 3 + aux_ALUControl [2:0] $end
$upscope $end
$upscope $end
$enddefinitions $end
$comment Show the parameter values. $end
$dumpall
b1010 "
$end
#0
$dumpvars
bx +
bx *
bx )
bx (
1'
1&
bx %
0$
bx #
bx !
$end
#50000
1$
#100000
b0 !
b0 (
b0 +
0$
b0 #
b0 )
#150000
1$
#200000
b1 !
b1 (
b1 +
0$
b1 #
b1 )
#250000
1$
#300000
0$
b0 %
b0 *
b10 #
b10 )
#350000
1$
#400000
b0 !
b0 (
b0 +
0$
0&
#450000
1$
#500000
b101 !
b101 (
b101 +
0$
b10 %
b10 *
#550000
1$
#600000
b11 !
b11 (
b11 +
0$
b110 %
b110 *
#650000
1$
#700000
b10 !
b10 (
b10 +
0$
b111 %
b111 *
#750000
1$
#800000
bx !
bx (
bx +
0$
b1 %
b1 *
#850000
1$
#900000
0$
b11 #
b11 )
